Metadata-Version: 2.1
Name: machine-parts-pp
Version: 0.0.1
Summary: Planted partitions over machine part data with part-of relations
Home-page: https://bitbucket.org/Bakkelund/machine-parts-pp/
Author: Daniel Bakkelund
Author-email: daniel.bakkelund@ifi.uio.no
License: UNKNOWN
Platform: UNKNOWN
Classifier: Programming Language :: Python :: 3
Classifier: License :: OSI Approved :: GNU Lesser General Public License v3 or later (LGPLv3+)
Classifier: Development Status :: 3 - Alpha
Classifier: Operating System :: OS Independent
Requires-Python: >=3.0
